README.md
setup.py
faradayio_cli/__init__.py
faradayio_cli/__main__.py
faradayio_cli/faradayio_cli.py
faradayio_cli.egg-info/PKG-INFO
faradayio_cli.egg-info/SOURCES.txt
faradayio_cli.egg-info/dependency_links.txt
faradayio_cli.egg-info/entry_points.txt
faradayio_cli.egg-info/requires.txt
faradayio_cli.egg-info/top_level.txt