Metadata-Version: 1.1
Name: faradayio-cli
Version: 0.0.4
Summary: FaradayRF TUN/TAP adapter command line interface
Home-page: https://github.com/FaradayRF/faradayio-cli
Author: FaradayRF
Author-email: Support@FaradayRF.com
License: GPLv3
Platform: UNKNOWN
Classifier: License :: OSI Approved :: GNU General Public License v3 (GPLv3)
Classifier: Programming Language :: Python
Classifier: Programming Language :: Python :: 3
Classifier: Topic :: Communications :: Ham Radio
Classifier: Operating System :: POSIX :: Linux
Classifier: Operating System :: Microsoft :: Windows
Classifier: Operating System :: MacOS :: MacOS X
Classifier: Development Status :: 2 - Pre-Alpha
Classifier: Intended Audience :: Developers
Classifier: Intended Audience :: Education
